bib2coa
