Metadata-Version: 2.1
Name: bib2coa
Version: 1.1
Summary: UNKNOWN
Home-page: UNKNOWN
Author: Alex Holehouse
Author-email: alex.holehouse@wustl.edu
License: MIT
Platform: UNKNOWN
